Metadata-Version: 2.1
Name: gvita
Version: 0.5.0
Summary: Little game based on Game of Life from John Conway
Home-page: https://github.com/me15degrees/game-of-life
Author: me15degrees
Author-email: me15degrees@gmail.com
License-File: LICENSE
